promptlink/__init__.py
promptlink/main.py
promptlink/requirements.txt
promptlink/static/index.html
promptlink-0.1.5.dist-info/WHEEL
promptlink-0.1.5.dist-info/LICENSE
promptlink-0.1.5.dist-info/METADATA
promptlink-0.1.5.dist-info/RECORD
