Metadata-Version: 2.1
Name: promptlink
Version: 0.1.5
Summary: Simplify user authentication and secure access from anywhere with customizable prompts and temporary links.
Author: Stéphane Thibaud
Author-email: snthibaud@gmail.com
Requires-Python: >=3.9,<4.0
Classifier: Programming Language :: Python :: 3
Classifier: Programming Language :: Python :: 3.9
Classifier: Programming Language :: Python :: 3.10
Classifier: Programming Language :: Python :: 3.11
Requires-Dist: Jinja2
Requires-Dist: functions-framework
Requires-Dist: google-cloud-functions
Requires-Dist: google-cloud-pubsub
Requires-Dist: google-cloud-storage
Requires-Dist: pyyaml
